CloudConfig/Rancher.py
CloudConfig/WriteFiles.py
CloudConfig/__init__.py
CloudConfig/lib/base.py
CloudConfig/lib/types.py
cloudconfig-0.2.2.dist-info/WHEEL
cloudconfig-0.2.2.dist-info/METADATA
cloudconfig-0.2.2.dist-info/RECORD
