Metadata-Version: 2.1
Name: cloudconfig
Version: 0.2.2
Summary: 
Home-page: https://github.com/Albus/CloudConfig
Keywords: rancheros,burmillaos,config,json,http
Author: Anton Rastyazhenko
Author-email: rastyazhenko.anton@gmail.com
Requires-Python: >=3.8,<4.0
Classifier: Programming Language :: Python :: 3
Classifier: Programming Language :: Python :: 3.8
Classifier: Programming Language :: Python :: 3.9
Requires-Dist: orjson (>=3.6.3,<4.0.0)
Requires-Dist: pathlib2 (>=2.3.6,<3.0.0)
Requires-Dist: pydantic (>=1.8.2,<2.0.0)
Requires-Dist: rsa (>=4.7.2,<5.0.0)
Requires-Dist: yarl (>=1.6.3,<2.0.0)
Project-URL: Repository, https://github.com/Albus/CloudConfig.git
